antichat/__init__.py
antichat/client.py
antichat/exceptions.py
antichat-0.0.7.dist-info/LICENSE
antichat-0.0.7.dist-info/METADATA
antichat-0.0.7.dist-info/WHEEL
antichat-0.0.7.dist-info/top_level.txt
antichat-0.0.7.dist-info/RECORD
