Metadata-Version: 2.1
Name: antichat
Version: 0.0.7
Summary: Simple forum.antichat.ru wrapper
Home-page: https://github.com/drygdryg/antichat_python
Author: drygdryg
Author-email: drygdryg2014@yandex.com
License: MIT
Download-URL: https://github.com/drygdryg/antichat_python/archive/v0.0.7.zip
Keywords: wrapper scraper antichat
Platform: UNKNOWN
Classifier: Development Status :: 3 - Alpha
Classifier: License :: OSI Approved :: MIT License
Classifier: Operating System :: OS Independent
Classifier: Programming Language :: Python :: 3.6
Classifier: Programming Language :: Python :: 3.7
Classifier: Programming Language :: Python :: 3.8
Classifier: Topic :: Internet :: WWW/HTTP
Classifier: Intended Audience :: Developers
Requires-Python: >=3.6
Requires-Dist: requests
Requires-Dist: beautifulsoup4
Requires-Dist: lxml
